{
	"name": "pipeline1",
	"properties": {
		"activities": [
			{
				"name": "Lookup_getmaxvalue",
				"type": "Lookup",
				"dependsOn": [],
				"policy": {
					"timeout": "7.00:00:00",
					"retry": 0,
					"retryIntervalInSeconds": 30,
					"secureOutput": false,
					"secureInput": false
				},
				"userProperties": [],
				"typeProperties": {
					"source": {
						"type": "AzureSqlSource",
						"sqlReaderQuery": "select max(cid) maxvalue from cust",
						"queryTimeout": "02:00:00",
						"partitionOption": "None"
					},
					"dataset": {
						"referenceName": "AzureSqlTable1",
						"type": "DatasetReference"
					}
				}
			},
			{
				"name": "Lookup_get_lpv",
				"type": "Lookup",
				"dependsOn": [],
				"policy": {
					"timeout": "7.00:00:00",
					"retry": 0,
					"retryIntervalInSeconds": 30,
					"secureOutput": false,
					"secureInput": false
				},
				"userProperties": [],
				"typeProperties": {
					"source": {
						"type": "AzureSqlSource",
						"sqlReaderQuery": "select*from watermark where tablename='cust'",
						"queryTimeout": "02:00:00",
						"partitionOption": "None"
					},
					"dataset": {
						"referenceName": "AzureSqlTable1",
						"type": "DatasetReference"
					}
				}
			},
			{
				"name": "Copy data1",
				"type": "Copy",
				"dependsOn": [
					{
						"activity": "Lookup_getmaxvalue",
						"dependencyConditions": [
							"Succeeded"
						]
					},
					{
						"activity": "Lookup_get_lpv",
						"dependencyConditions": [
							"Succeeded"
						]
					}
				],
				"policy": {
					"timeout": "7.00:00:00",
					"retry": 0,
					"retryIntervalInSeconds": 30,
					"secureOutput": false,
					"secureInput": false
				},
				"userProperties": [],
				"typeProperties": {
					"source": {
						"type": "AzureSqlSource",
						"sqlReaderQuery": {
							"value": "@select*from cust where cid>@(activity('Lookup_get_lpv').output.firstrow.last_processed_value)",
							"type": "Expression"
						},
						"queryTimeout": "02:00:00",
						"partitionOption": "None"
					},
					"sink": {
						"type": "JsonSink",
						"storeSettings": {
							"type": "AzureBlobStorageWriteSettings"
						},
						"formatSettings": {
							"type": "JsonWriteSettings"
						}
					},
					"enableStaging": false
				},
				"inputs": [
					{
						"referenceName": "AzureSqlTable1",
						"type": "DatasetReference"
					}
				],
				"outputs": [
					{
						"referenceName": "Json1",
						"type": "DatasetReference"
					}
				]
			},
			{
				"name": "Stored procedure1",
				"type": "SqlServerStoredProcedure",
				"dependsOn": [
					{
						"activity": "Copy data1",
						"dependencyConditions": [
							"Succeeded"
						]
					}
				],
				"policy": {
					"timeout": "7.00:00:00",
					"retry": 0,
					"retryIntervalInSeconds": 30,
					"secureOutput": false,
					"secureInput": false
				},
				"userProperties": [],
				"typeProperties": {
					"storedProcedureName": "[dbo].[watermark_usp]",
					"storedProcedureParameters": {
						"lpv": {
							"value": {
								"value": "@activity('Lookup_getmaxvalue').output.firstrow.maxvalue",
								"type": "Expression"
							},
							"type": "String"
						},
						"tname": {
							"value": {
								"value": "@activity('Lookup_get_lpv').output.firstrow.tablename",
								"type": "Expression"
							},
							"type": "String"
						}
					}
				},
				"linkedServiceName": {
					"referenceName": "AzureSqlDatabase1",
					"type": "LinkedServiceReference"
				}
			}
		],
		"annotations": []
	}
}